SecretF/__init__.py
SecretF/main.py
SecretF-1.101.2.dist-info/LICENSE.txt
SecretF-1.101.2.dist-info/METADATA
SecretF-1.101.2.dist-info/WHEEL
SecretF-1.101.2.dist-info/top_level.txt
SecretF-1.101.2.dist-info/RECORD
