Metadata-Version: 2.1
Name: SecretF
Version: 1.101.2
Summary: Secret File
Home-page: https://github.com/HardHook/SecretF
Author: Fedorenko Timur
Author-email: tim.fedorenko@mail.ru
License: UNKNOWN
Platform: UNKNOWN
Classifier: Operating System :: Microsoft :: Windows :: Windows 10
Classifier: Programming Language :: Python :: 3.9
License-File: LICENSE.txt
